dynalite_pdeg.py
dynalite_pdeg-0.0.2.dist-info/METADATA
dynalite_pdeg-0.0.2.dist-info/WHEEL
dynalite_pdeg-0.0.2.dist-info/licenses/LICENSE
dynalite_pdeg-0.0.2.dist-info/RECORD
