Metadata-Version: 2.3
Name: dynalite_pdeg
Version: 0.0.2
Summary: An API for the Dynalite PDEG, using telnet
Project-URL: Homepage, https://github.com/patrickpmueller/dynalite-pdeg
Project-URL: Issues, https://github.com/patrickpmueller/dynalite-pdeg/issues
Author-email: Patrick Pellacani Muller <patrickpmueller@proton.me>
Classifier: License :: OSI Approved :: MIT License
Classifier: Operating System :: OS Independent
Classifier: Programming Language :: Python :: 3
Requires-Python: >=3.11
Requires-Dist: aiohttp
Requires-Dist: asyncio-telnet
